LICENSE
README.rst
setup.cfg
setup.py
conoha/__init__.py
conoha/api.py
conoha/block.py
conoha/cli.py
conoha/compute.py
conoha/config.py
conoha/dns.py
conoha/error.py
conoha/image.py
conoha/network.py
conoha_cli.egg-info/PKG-INFO
conoha_cli.egg-info/SOURCES.txt
conoha_cli.egg-info/dependency_links.txt
conoha_cli.egg-info/entry_points.txt
conoha_cli.egg-info/not-zip-safe
conoha_cli.egg-info/requires.txt
conoha_cli.egg-info/top_level.txt