Metadata-Version: 2.1
Name: conoha-cli
Version: 0.3.0
Summary: conoha-cli is a command and Python3 library for ConoHa API.
Home-page: https://github.com/yuuki0xff/conoha-cli
Author: yuuki0xff
Author-email: yuuki0xff@gmail.com
License: MIT
Keywords: conoha cli api library cloud
Classifier: Development Status :: 5 - Production/Stable
Classifier: Environment :: Console
Classifier: Intended Audience :: Developers
Classifier: Intended Audience :: System Administrators
Classifier: License :: OSI Approved :: MIT License
Classifier: Natural Language :: Japanese
Classifier: Operating System :: POSIX :: Linux
Classifier: Programming Language :: Python :: 3
Classifier: Programming Language :: Python :: 3 :: Only
Classifier: Programming Language :: Python :: Implementation :: CPython
Classifier: Topic :: Utilities
License-File: LICENSE
